ClassMaker/__init__.py
ClassMaker-0.1.dist-info/LICENCE
ClassMaker-0.1.dist-info/METADATA
ClassMaker-0.1.dist-info/WHEEL
ClassMaker-0.1.dist-info/top_level.txt
ClassMaker-0.1.dist-info/RECORD
